{
  "FireBladeMod:BurningPower": {
    "NAME": "Burning",
    "DESCRIPTIONS": [
      "Losing ",
      " HP each turn."
    ]
  },
  "FireBladeMod:PyroPower": {
    "NAME": "Fervor",
    "DESCRIPTIONS": [
      "When you apply #yBurning, you apply #b",
      " extra.",
      " less."
    ]
  },
  "FireBladeMod:DefFlamesPower": {
    "NAME": "Defensive Flames",
    "DESCRIPTIONS": [
      "Whenever you play a card that applies Burning, gain #b",
      " #yBlock."
    ]
  },
  "FireBladeMod:ReservesPower": {
    "NAME": "Reserves",
    "DESCRIPTIONS": [
      "At the end of your turn each [R] you have becomes #b",
      " #yBlock."
    ]
  },
  "FireBladeMod:FlameFormPower": {
    "NAME": "Flame Form",
    "DESCRIPTIONS": [
      "Whenever you deal attack damage, also apply #b",
      " #yBurning."
    ]
  },
  "FireBladeMod:TungstenPower": {
    "NAME": "Tungsten Skin",
    "DESCRIPTIONS": [
      "You receive #b",
      " less damage each time you take damage."
    ]
  },
  "FireBladeMod:SuddenStrikesPower": {
    "NAME": "Sudden Strikes",
    "DESCRIPTIONS": ["When you play an attack card, make #b",
      " extra attack on a random enemy for ",
      " extra attacks on a random enemy for ",
      " damage."
    ]
  },
  "FireBladeMod:SuddenStrikesPlusPower": {
    "NAME": "Sudden Strikes Plus",
    "DESCRIPTIONS": ["When you play an attack card, make #b",
      " extra attack on all enemies for ",
      " extra attacks on all enemies for ",
      " damage."
    ]
  },
  "FireBladeMod:AfterBurnPower": {
    "NAME": "After Burn",
    "DESCRIPTIONS": [
      "Each time you play a card, gain #b",
      " #yFire #yShield."
    ]
  },
  "FireBladeMod:FireShieldPower": {
    "NAME": "Fire Shield",
    "DESCRIPTIONS": [
      "Each time you are attacked this turn, deal #b",
      " damage back."
    ]
  },
  "FireBladeMod:ClingingFlamesPower": {
    "NAME": "Fire Shield",
    "DESCRIPTIONS": [
      "Each time you are attacked this turn, deal #b",
      " #yBurning to the attacker."
    ]
  }
}